setup.py
gaussian_binomial_probablity_distribution/Binomialdistribution.py
gaussian_binomial_probablity_distribution/Gaussiandistribution.py
gaussian_binomial_probablity_distribution/Generaldistribution.py
gaussian_binomial_probablity_distribution/__init__.py
gaussian_binomial_probablity_distribution.egg-info/PKG-INFO
gaussian_binomial_probablity_distribution.egg-info/SOURCES.txt
gaussian_binomial_probablity_distribution.egg-info/dependency_links.txt
gaussian_binomial_probablity_distribution.egg-info/not-zip-safe
gaussian_binomial_probablity_distribution.egg-info/top_level.txt