Metadata-Version: 1.0
Name: gaussian-binomial-probablity-distribution
Version: 0.1
Summary: Gaussian and Binomial distributions
Home-page: UNKNOWN
Author: Tejendra Pratap
Author-email: tejendra.pratap.ju@gmail.com
License: UNKNOWN
Platform: UNKNOWN
